{
   "payload": {
      "market": 90,
      "code": "BK0879",
      "name": "标准普尔",
      "pinyin": "BZPE",
      "type": 3,
      "flag": 0
   },
   "maxRetries": 3,
   "errorPageRetries": 0,
   "pageSize": 20,
   "totalPages": 53,
   "completePages": [
      1,
      28,
      8,
      27,
      3,
      34,
      9,
      48,
      4,
      11,
      40,
      37,
      2,
      22,
      44,
      32,
      29,
      24,
      6,
      43,
      26,
      51,
      12,
      36,
      39
   ],
   "pendingPages": [
      47,
      53,
      35,
      46,
      50,
      41,
      45,
      42,
      16,
      7,
      33,
      17,
      21,
      10,
      23,
      19,
      31,
      49,
      20,
      5,
      18,
      52,
      38,
      14,
      30,
      13,
      15,
      25
   ],
   "currentPage": 47,
   "completePageShares": {
      "p1": [
         {
            "code": "603997",
            "name": "继峰股份"
         },
         {
            "code": "603993",
            "name": "洛阳钼业"
         },
         {
            "code": "603989",
            "name": "艾华集团"
         },
         {
            "code": "603986",
            "name": "兆易创新"
         },
         {
            "code": "603959",
            "name": "百利科技"
         },
         {
            "code": "603939",
            "name": "益丰药房"
         },
         {
            "code": "603929",
            "name": "亚翔集成"
         },
         {
            "code": "603899",
            "name": "晨光股份"
         },
         {
            "code": "603898",
            "name": "好莱客"
         },
         {
            "code": "603897",
            "name": "长城科技"
         },
         {
            "code": "603895",
            "name": "天永智能"
         },
         {
            "code": "603888",
            "name": "新华网"
         },
         {
            "code": "603885",
            "name": "吉祥航空"
         },
         {
            "code": "603883",
            "name": "老百姓"
         },
         {
            "code": "603882",
            "name": "金域医学"
         },
         {
            "code": "603881",
            "name": "数据港"
         },
         {
            "code": "603877",
            "name": "太平鸟"
         },
         {
            "code": "603876",
            "name": "鼎胜新材"
         },
         {
            "code": "603871",
            "name": "嘉友国际"
         },
         {
            "code": "603868",
            "name": "飞科电器"
         }
      ],
      "p28": [
         {
            "code": "600028",
            "name": "中国石化"
         },
         {
            "code": "600027",
            "name": "华电国际"
         },
         {
            "code": "600026",
            "name": "中远海能"
         },
         {
            "code": "600025",
            "name": "华能水电"
         },
         {
            "code": "600021",
            "name": "上海电力"
         },
         {
            "code": "600020",
            "name": "中原高速"
         },
         {
            "code": "600019",
            "name": "宝钢股份"
         },
         {
            "code": "600018",
            "name": "上港集团"
         },
         {
            "code": "600016",
            "name": "民生银行"
         },
         {
            "code": "600015",
            "name": "华夏银行"
         },
         {
            "code": "600012",
            "name": "皖通高速"
         },
         {
            "code": "600011",
            "name": "华能国际"
         },
         {
            "code": "600010",
            "name": "包钢股份"
         },
         {
            "code": "600009",
            "name": "上海机场"
         },
         {
            "code": "600007",
            "name": "中国国贸"
         },
         {
            "code": "600004",
            "name": "白云机场"
         },
         {
            "code": "600000",
            "name": "浦发银行"
         },
         {
            "code": "002948",
            "name": "青岛银行"
         },
         {
            "code": "002939",
            "name": "长城证券"
         },
         {
            "code": "002938",
            "name": "鹏鼎控股"
         }
      ],
      "p8": [
         {
            "code": "601933",
            "name": "永辉超市"
         },
         {
            "code": "601919",
            "name": "中远海控"
         },
         {
            "code": "601908",
            "name": "京运通"
         },
         {
            "code": "601901",
            "name": "方正证券"
         },
         {
            "code": "601899",
            "name": "紫金矿业"
         },
         {
            "code": "601898",
            "name": "中煤能源"
         },
         {
            "code": "601888",
            "name": "中国中免"
         },
         {
            "code": "601881",
            "name": "中国银河"
         },
         {
            "code": "601880",
            "name": "辽港股份"
         },
         {
            "code": "601878",
            "name": "浙商证券"
         },
         {
            "code": "601877",
            "name": "正泰电器"
         },
         {
            "code": "601872",
            "name": "招商轮船"
         },
         {
            "code": "601869",
            "name": "长飞光纤"
         },
         {
            "code": "601866",
            "name": "中远海发"
         },
         {
            "code": "601865",
            "name": "福莱特"
         },
         {
            "code": "601860",
            "name": "紫金银行"
         },
         {
            "code": "601858",
            "name": "中国科传"
         },
         {
            "code": "601857",
            "name": "中国石油"
         },
         {
            "code": "601838",
            "name": "成都银行"
         },
         {
            "code": "601828",
            "name": "美凯龙"
         }
      ],
      "p27": [
         {
            "code": "600094",
            "name": "大名城"
         },
         {
            "code": "600089",
            "name": "特变电工"
         },
         {
            "code": "600085",
            "name": "同仁堂"
         },
         {
            "code": "600075",
            "name": "新疆天业"
         },
         {
            "code": "600073",
            "name": "光明肉业"
         },
         {
            "code": "600072",
            "name": "中船科技"
         },
         {
            "code": "600066",
            "name": "宇通客车"
         },
         {
            "code": "600062",
            "name": "华润双鹤"
         },
         {
            "code": "600061",
            "name": "国投资本"
         },
         {
            "code": "600060",
            "name": "海信视像"
         },
         {
            "code": "600056",
            "name": "中国医药"
         },
         {
            "code": "600053",
            "name": "九鼎投资"
         },
         {
            "code": "600050",
            "name": "中国联通"
         },
         {
            "code": "600048",
            "name": "保利发展"
         },
         {
            "code": "600039",
            "name": "四川路桥"
         },
         {
            "code": "600038",
            "name": "中直股份"
         },
         {
            "code": "600036",
            "name": "招商银行"
         },
         {
            "code": "600031",
            "name": "三一重工"
         },
         {
            "code": "600030",
            "name": "中信证券"
         },
         {
            "code": "600029",
            "name": "南方航空"
         }
      ],
      "p3": [
         {
            "code": "603708",
            "name": "家家悦"
         },
         {
            "code": "603707",
            "name": "健友股份"
         },
         {
            "code": "603686",
            "name": "福龙马"
         },
         {
            "code": "603680",
            "name": "今创集团"
         },
         {
            "code": "603669",
            "name": "灵康药业"
         },
         {
            "code": "603666",
            "name": "亿嘉和"
         },
         {
            "code": "603660",
            "name": "苏州科达"
         },
         {
            "code": "603659",
            "name": "璞泰来"
         },
         {
            "code": "603658",
            "name": "安图生物"
         },
         {
            "code": "603650",
            "name": "彤程新材"
         },
         {
            "code": "603639",
            "name": "海利尔"
         },
         {
            "code": "603638",
            "name": "艾迪精密"
         },
         {
            "code": "603626",
            "name": "科森科技"
         },
         {
            "code": "603619",
            "name": "中曼石油"
         },
         {
            "code": "603612",
            "name": "索通发展"
         },
         {
            "code": "603609",
            "name": "禾丰股份"
         },
         {
            "code": "603600",
            "name": "永艺股份"
         },
         {
            "code": "603599",
            "name": "广信股份"
         },
         {
            "code": "603596",
            "name": "伯特利"
         },
         {
            "code": "603595",
            "name": "ST东尼"
         }
      ],
      "p34": [
         {
            "code": "002506",
            "name": "协鑫集成"
         },
         {
            "code": "002500",
            "name": "山西证券"
         },
         {
            "code": "002498",
            "name": "汉缆股份"
         },
         {
            "code": "002497",
            "name": "雅化集团"
         },
         {
            "code": "002493",
            "name": "荣盛石化"
         },
         {
            "code": "002491",
            "name": "通鼎互联"
         },
         {
            "code": "002490",
            "name": "山东墨龙"
         },
         {
            "code": "002489",
            "name": "浙江永强"
         },
         {
            "code": "002488",
            "name": "金固股份"
         },
         {
            "code": "002482",
            "name": "广田集团"
         },
         {
            "code": "002475",
            "name": "立讯精密"
         },
         {
            "code": "002468",
            "name": "申通快递"
         },
         {
            "code": "002466",
            "name": "天齐锂业"
         },
         {
            "code": "002465",
            "name": "海格通信"
         },
         {
            "code": "002463",
            "name": "沪电股份"
         },
         {
            "code": "002461",
            "name": "珠江啤酒"
         },
         {
            "code": "002460",
            "name": "赣锋锂业"
         },
         {
            "code": "002458",
            "name": "益生股份"
         },
         {
            "code": "002456",
            "name": "欧菲光"
         },
         {
            "code": "002449",
            "name": "国星光电"
         }
      ],
      "p9": [
         {
            "code": "601818",
            "name": "光大银行"
         },
         {
            "code": "601811",
            "name": "新华文轩"
         },
         {
            "code": "601808",
            "name": "中海油服"
         },
         {
            "code": "601801",
            "name": "皖新传媒"
         },
         {
            "code": "601800",
            "name": "中国交建"
         },
         {
            "code": "601799",
            "name": "星宇股份"
         },
         {
            "code": "601789",
            "name": "宁波建工"
         },
         {
            "code": "601788",
            "name": "光大证券"
         },
         {
            "code": "601766",
            "name": "中国中车"
         },
         {
            "code": "601727",
            "name": "上海电气"
         },
         {
            "code": "601717",
            "name": "中创智领"
         },
         {
            "code": "601699",
            "name": "潞安环能"
         },
         {
            "code": "601689",
            "name": "拓普集团"
         },
         {
            "code": "601688",
            "name": "华泰证券"
         },
         {
            "code": "601678",
            "name": "滨化股份"
         },
         {
            "code": "601669",
            "name": "中国电建"
         },
         {
            "code": "601668",
            "name": "中国建筑"
         },
         {
            "code": "601666",
            "name": "平煤股份"
         },
         {
            "code": "601636",
            "name": "旗滨集团"
         },
         {
            "code": "601633",
            "name": "长城汽车"
         }
      ],
      "p48": [
         {
            "code": "000718",
            "name": "苏宁环球"
         },
         {
            "code": "000717",
            "name": "中南股份"
         },
         {
            "code": "000712",
            "name": "锦龙股份"
         },
         {
            "code": "000710",
            "name": "贝瑞基因"
         },
         {
            "code": "000709",
            "name": "河钢股份"
         },
         {
            "code": "000703",
            "name": "恒逸石化"
         },
         {
            "code": "000690",
            "name": "宝新能源"
         },
         {
            "code": "000688",
            "name": "国城矿业"
         },
         {
            "code": "000686",
            "name": "东北证券"
         },
         {
            "code": "000685",
            "name": "中山公用"
         },
         {
            "code": "000683",
            "name": "博源化工"
         },
         {
            "code": "000681",
            "name": "视觉中国"
         },
         {
            "code": "000676",
            "name": "智度股份"
         },
         {
            "code": "000661",
            "name": "长春高新"
         },
         {
            "code": "000656",
            "name": "*ST金科"
         },
         {
            "code": "000651",
            "name": "格力电器"
         },
         {
            "code": "000650",
            "name": "仁和药业"
         },
         {
            "code": "000639",
            "name": "西王食品"
         },
         {
            "code": "000631",
            "name": "顺发恒能"
         },
         {
            "code": "000630",
            "name": "铜陵有色"
         }
      ],
      "p4": [
         {
            "code": "603590",
            "name": "康辰药业"
         },
         {
            "code": "603589",
            "name": "口子窖"
         },
         {
            "code": "603588",
            "name": "高能环境"
         },
         {
            "code": "603587",
            "name": "地素时尚"
         },
         {
            "code": "603585",
            "name": "苏利股份"
         },
         {
            "code": "603583",
            "name": "捷昌驱动"
         },
         {
            "code": "603579",
            "name": "荣泰健康"
         },
         {
            "code": "603569",
            "name": "长久物流"
         },
         {
            "code": "603568",
            "name": "伟明环保"
         },
         {
            "code": "603556",
            "name": "海兴电力"
         },
         {
            "code": "603533",
            "name": "掌阅科技"
         },
         {
            "code": "603517",
            "name": "ST绝味"
         },
         {
            "code": "603515",
            "name": "欧普照明"
         },
         {
            "code": "603505",
            "name": "金石资源"
         },
         {
            "code": "603501",
            "name": "豪威集团"
         },
         {
            "code": "603486",
            "name": "科沃斯"
         },
         {
            "code": "603466",
            "name": "风语筑"
         },
         {
            "code": "603444",
            "name": "吉比特"
         },
         {
            "code": "603421",
            "name": "鼎信通讯"
         },
         {
            "code": "603393",
            "name": "新天然气"
         }
      ],
      "p11": [
         {
            "code": "601328",
            "name": "交通银行"
         },
         {
            "code": "601326",
            "name": "秦港股份"
         },
         {
            "code": "601319",
            "name": "中国人保"
         },
         {
            "code": "601318",
            "name": "中国平安"
         },
         {
            "code": "601311",
            "name": "骆驼股份"
         },
         {
            "code": "601298",
            "name": "青岛港"
         },
         {
            "code": "601288",
            "name": "农业银行"
         },
         {
            "code": "601238",
            "name": "广汽集团"
         },
         {
            "code": "601233",
            "name": "桐昆股份"
         },
         {
            "code": "601231",
            "name": "环旭电子"
         },
         {
            "code": "601229",
            "name": "上海银行"
         },
         {
            "code": "601225",
            "name": "陕西煤业"
         },
         {
            "code": "601222",
            "name": "林洋能源"
         },
         {
            "code": "601216",
            "name": "君正集团"
         },
         {
            "code": "601211",
            "name": "国泰海通"
         },
         {
            "code": "601200",
            "name": "上海环境"
         },
         {
            "code": "601198",
            "name": "东兴证券"
         },
         {
            "code": "601186",
            "name": "中国铁建"
         },
         {
            "code": "601169",
            "name": "北京银行"
         },
         {
            "code": "601168",
            "name": "西部矿业"
         }
      ],
      "p40": [
         {
            "code": "002180",
            "name": "纳思达"
         },
         {
            "code": "002179",
            "name": "中航光电"
         },
         {
            "code": "002176",
            "name": "江特电机"
         },
         {
            "code": "002174",
            "name": "游族网络"
         },
         {
            "code": "002171",
            "name": "楚江新材"
         },
         {
            "code": "002168",
            "name": "*ST惠程"
         },
         {
            "code": "002157",
            "name": "正邦科技"
         },
         {
            "code": "002156",
            "name": "通富微电"
         },
         {
            "code": "002155",
            "name": "湖南黄金"
         },
         {
            "code": "002153",
            "name": "石基信息"
         },
         {
            "code": "002152",
            "name": "广电运通"
         },
         {
            "code": "002151",
            "name": "北斗星通"
         },
         {
            "code": "002146",
            "name": "荣盛发展"
         },
         {
            "code": "002145",
            "name": "钛能化学"
         },
         {
            "code": "002142",
            "name": "宁波银行"
         },
         {
            "code": "002138",
            "name": "顺络电子"
         },
         {
            "code": "002131",
            "name": "利欧股份"
         },
         {
            "code": "002129",
            "name": "TCL中环"
         },
         {
            "code": "002128",
            "name": "电投能源"
         },
         {
            "code": "002127",
            "name": "南极电商"
         }
      ],
      "p37": [
         {
            "code": "002366",
            "name": "融发核电"
         },
         {
            "code": "002364",
            "name": "中恒电气"
         },
         {
            "code": "002358",
            "name": "森源电气"
         },
         {
            "code": "002353",
            "name": "杰瑞股份"
         },
         {
            "code": "002352",
            "name": "顺丰控股"
         },
         {
            "code": "002344",
            "name": "海宁皮城"
         },
         {
            "code": "002340",
            "name": "格林美"
         },
         {
            "code": "002332",
            "name": "仙琚制药"
         },
         {
            "code": "002327",
            "name": "富安娜"
         },
         {
            "code": "002326",
            "name": "永太科技"
         },
         {
            "code": "002320",
            "name": "海峡股份"
         },
         {
            "code": "002318",
            "name": "久立特材"
         },
         {
            "code": "002317",
            "name": "众生药业"
         },
         {
            "code": "002314",
            "name": "南山控股"
         },
         {
            "code": "002313",
            "name": "日海智能"
         },
         {
            "code": "002311",
            "name": "海大集团"
         },
         {
            "code": "002310",
            "name": "东方新能"
         },
         {
            "code": "002309",
            "name": "中利集团"
         },
         {
            "code": "002304",
            "name": "洋河股份"
         },
         {
            "code": "002303",
            "name": "美盈森"
         }
      ],
      "p2": [
         {
            "code": "603866",
            "name": "桃李面包"
         },
         {
            "code": "603858",
            "name": "步长制药"
         },
         {
            "code": "603848",
            "name": "好太太"
         },
         {
            "code": "603833",
            "name": "欧派家居"
         },
         {
            "code": "603816",
            "name": "顾家家居"
         },
         {
            "code": "603808",
            "name": "歌力思"
         },
         {
            "code": "603806",
            "name": "福斯特"
         },
         {
            "code": "603803",
            "name": "瑞斯康达"
         },
         {
            "code": "603801",
            "name": "志邦家居"
         },
         {
            "code": "603799",
            "name": "华友钴业"
         },
         {
            "code": "603773",
            "name": "沃格光电"
         },
         {
            "code": "603766",
            "name": "隆鑫通用"
         },
         {
            "code": "603757",
            "name": "大元泵业"
         },
         {
            "code": "603737",
            "name": "三棵树"
         },
         {
            "code": "603733",
            "name": "仙鹤股份"
         },
         {
            "code": "603730",
            "name": "岱美股份"
         },
         {
            "code": "603728",
            "name": "鸣志电器"
         },
         {
            "code": "603713",
            "name": "密尔克卫"
         },
         {
            "code": "603712",
            "name": "七一二"
         },
         {
            "code": "603711",
            "name": "香飘飘"
         }
      ],
      "p22": [
         {
            "code": "600446",
            "name": "金证股份"
         },
         {
            "code": "600439",
            "name": "瑞贝卡"
         },
         {
            "code": "600438",
            "name": "通威股份"
         },
         {
            "code": "600436",
            "name": "片仔癀"
         },
         {
            "code": "600426",
            "name": "华鲁恒升"
         },
         {
            "code": "600422",
            "name": "昆药集团"
         },
         {
            "code": "600420",
            "name": "国药现代"
         },
         {
            "code": "600418",
            "name": "江淮汽车"
         },
         {
            "code": "600415",
            "name": "小商品城"
         },
         {
            "code": "600410",
            "name": "华胜天成"
         },
         {
            "code": "600409",
            "name": "三友化工"
         },
         {
            "code": "600406",
            "name": "国电南瑞"
         },
         {
            "code": "600398",
            "name": "海澜之家"
         },
         {
            "code": "600395",
            "name": "盘江股份"
         },
         {
            "code": "600392",
            "name": "盛和资源"
         },
         {
            "code": "600388",
            "name": "龙净环保"
         },
         {
            "code": "600383",
            "name": "金地集团"
         },
         {
            "code": "600380",
            "name": "健康元"
         },
         {
            "code": "600377",
            "name": "宁沪高速"
         },
         {
            "code": "600376",
            "name": "首开股份"
         }
      ],
      "p44": [
         {
            "code": "000988",
            "name": "华工科技"
         },
         {
            "code": "000987",
            "name": "越秀资本"
         },
         {
            "code": "000983",
            "name": "山西焦煤"
         },
         {
            "code": "000980",
            "name": "众泰汽车"
         },
         {
            "code": "000977",
            "name": "浪潮信息"
         },
         {
            "code": "000975",
            "name": "山金国际"
         },
         {
            "code": "000970",
            "name": "中科三环"
         },
         {
            "code": "000969",
            "name": "安泰科技"
         },
         {
            "code": "000968",
            "name": "蓝焰控股"
         },
         {
            "code": "000963",
            "name": "华东医药"
         },
         {
            "code": "000960",
            "name": "锡业股份"
         },
         {
            "code": "000959",
            "name": "首钢股份"
         },
         {
            "code": "000951",
            "name": "中国重汽"
         },
         {
            "code": "000950",
            "name": "重药控股"
         },
         {
            "code": "000938",
            "name": "紫光股份"
         },
         {
            "code": "000937",
            "name": "冀中能源"
         },
         {
            "code": "000936",
            "name": "华西股份"
         },
         {
            "code": "000935",
            "name": "四川双马"
         },
         {
            "code": "000933",
            "name": "神火股份"
         },
         {
            "code": "000932",
            "name": "华菱钢铁"
         }
      ],
      "p32": [
         {
            "code": "002635",
            "name": "安洁科技"
         },
         {
            "code": "002626",
            "name": "金达威"
         },
         {
            "code": "002625",
            "name": "光启技术"
         },
         {
            "code": "002624",
            "name": "完美世界"
         },
         {
            "code": "002614",
            "name": "奥佳华"
         },
         {
            "code": "002611",
            "name": "东方精工"
         },
         {
            "code": "002608",
            "name": "江苏国信"
         },
         {
            "code": "002607",
            "name": "中公教育"
         },
         {
            "code": "002603",
            "name": "以岭药业"
         },
         {
            "code": "002602",
            "name": "世纪华通"
         },
         {
            "code": "002601",
            "name": "龙佰集团"
         },
         {
            "code": "002600",
            "name": "领益智造"
         },
         {
            "code": "002597",
            "name": "金禾实业"
         },
         {
            "code": "002596",
            "name": "海南瑞泽"
         },
         {
            "code": "002595",
            "name": "豪迈科技"
         },
         {
            "code": "002594",
            "name": "比亚迪"
         },
         {
            "code": "002589",
            "name": "瑞康医药"
         },
         {
            "code": "002585",
            "name": "双星新材"
         },
         {
            "code": "002583",
            "name": "海能达"
         },
         {
            "code": "002573",
            "name": "清新环境"
         }
      ],
      "p29": [
         {
            "code": "002936",
            "name": "郑州银行"
         },
         {
            "code": "002930",
            "name": "宏川智慧"
         },
         {
            "code": "002929",
            "name": "润建股份"
         },
         {
            "code": "002928",
            "name": "华夏航空"
         },
         {
            "code": "002926",
            "name": "华西证券"
         },
         {
            "code": "002925",
            "name": "盈趣科技"
         },
         {
            "code": "002920",
            "name": "德赛西威"
         },
         {
            "code": "002916",
            "name": "深南电路"
         },
         {
            "code": "002913",
            "name": "奥士康"
         },
         {
            "code": "002912",
            "name": "中新赛克"
         },
         {
            "code": "002911",
            "name": "佛燃能源"
         },
         {
            "code": "002910",
            "name": "庄园牧场"
         },
         {
            "code": "002907",
            "name": "华森制药"
         },
         {
            "code": "002901",
            "name": "大博医疗"
         },
         {
            "code": "002867",
            "name": "周大生"
         },
         {
            "code": "002859",
            "name": "洁美科技"
         },
         {
            "code": "002851",
            "name": "麦格米特"
         },
         {
            "code": "002841",
            "name": "视源股份"
         },
         {
            "code": "002839",
            "name": "张家港行"
         },
         {
            "code": "002832",
            "name": "比音勒芬"
         }
      ],
      "p24": [
         {
            "code": "600323",
            "name": "瀚蓝环境"
         },
         {
            "code": "600315",
            "name": "上海家化"
         },
         {
            "code": "600312",
            "name": "平高电气"
         },
         {
            "code": "600310",
            "name": "广西能源"
         },
         {
            "code": "600309",
            "name": "万华化学"
         },
         {
            "code": "600305",
            "name": "恒顺醋业"
         },
         {
            "code": "600299",
            "name": "安迪苏"
         },
         {
            "code": "600298",
            "name": "安琪酵母"
         },
         {
            "code": "600295",
            "name": "鄂尔多斯"
         },
         {
            "code": "600285",
            "name": "羚锐制药"
         },
         {
            "code": "600284",
            "name": "浦东建设"
         },
         {
            "code": "600282",
            "name": "南钢股份"
         },
         {
            "code": "600276",
            "name": "恒瑞医药"
         },
         {
            "code": "600273",
            "name": "嘉化能源"
         },
         {
            "code": "600271",
            "name": "航天信息"
         },
         {
            "code": "600261",
            "name": "阳光照明"
         },
         {
            "code": "600258",
            "name": "首旅酒店"
         },
         {
            "code": "600256",
            "name": "广汇能源"
         },
         {
            "code": "600252",
            "name": "中恒集团"
         },
         {
            "code": "600239",
            "name": "云南城投"
         }
      ],
      "p6": [
         {
            "code": "603233",
            "name": "大参林"
         },
         {
            "code": "603228",
            "name": "景旺电子"
         },
         {
            "code": "603225",
            "name": "新凤鸣"
         },
         {
            "code": "603220",
            "name": "中贝通信"
         },
         {
            "code": "603198",
            "name": "迎驾贡酒"
         },
         {
            "code": "603185",
            "name": "弘元绿能"
         },
         {
            "code": "603180",
            "name": "金牌家居"
         },
         {
            "code": "603165",
            "name": "荣晟环保"
         },
         {
            "code": "603160",
            "name": "汇顶科技"
         },
         {
            "code": "603156",
            "name": "养元饮品"
         },
         {
            "code": "603128",
            "name": "华贸物流"
         },
         {
            "code": "603127",
            "name": "昭衍新药"
         },
         {
            "code": "603126",
            "name": "中材节能"
         },
         {
            "code": "603121",
            "name": "华培动力"
         },
         {
            "code": "603118",
            "name": "共进股份"
         },
         {
            "code": "603113",
            "name": "金能科技"
         },
         {
            "code": "603108",
            "name": "润达医疗"
         },
         {
            "code": "603103",
            "name": "横店影视"
         },
         {
            "code": "603098",
            "name": "森特股份"
         },
         {
            "code": "603080",
            "name": "新疆火炬"
         }
      ],
      "p43": [
         {
            "code": "002025",
            "name": "航天电器"
         },
         {
            "code": "002024",
            "name": "ST易购"
         },
         {
            "code": "002023",
            "name": "海特高新"
         },
         {
            "code": "002020",
            "name": "京新药业"
         },
         {
            "code": "002019",
            "name": "亿帆医药"
         },
         {
            "code": "002016",
            "name": "世荣兆业"
         },
         {
            "code": "002010",
            "name": "传化智联"
         },
         {
            "code": "002008",
            "name": "大族激光"
         },
         {
            "code": "002007",
            "name": "华兰生物"
         },
         {
            "code": "002004",
            "name": "华邦健康"
         },
         {
            "code": "002001",
            "name": "新 和 成"
         },
         {
            "code": "001979",
            "name": "招商蛇口"
         },
         {
            "code": "001965",
            "name": "招商公路"
         },
         {
            "code": "001872",
            "name": "招商港口"
         },
         {
            "code": "001696",
            "name": "宗申动力"
         },
         {
            "code": "000999",
            "name": "华润三九"
         },
         {
            "code": "000998",
            "name": "隆平高科"
         },
         {
            "code": "000997",
            "name": "新 大 陆"
         },
         {
            "code": "000990",
            "name": "诚志股份"
         },
         {
            "code": "000989",
            "name": "九芝堂"
         }
      ],
      "p26": [
         {
            "code": "600167",
            "name": "联美控股"
         },
         {
            "code": "600162",
            "name": "香江控股"
         },
         {
            "code": "600161",
            "name": "天坛生物"
         },
         {
            "code": "600160",
            "name": "巨化股份"
         },
         {
            "code": "600153",
            "name": "建发股份"
         },
         {
            "code": "600141",
            "name": "兴发集团"
         },
         {
            "code": "600138",
            "name": "中青旅"
         },
         {
            "code": "600136",
            "name": "ST明诚"
         },
         {
            "code": "600132",
            "name": "重庆啤酒"
         },
         {
            "code": "600125",
            "name": "铁龙物流"
         },
         {
            "code": "600123",
            "name": "兰花科创"
         },
         {
            "code": "600120",
            "name": "浙江东方"
         },
         {
            "code": "600118",
            "name": "中国卫星"
         },
         {
            "code": "600116",
            "name": "三峡水利"
         },
         {
            "code": "600115",
            "name": "中国东航"
         },
         {
            "code": "600114",
            "name": "东睦股份"
         },
         {
            "code": "600111",
            "name": "北方稀土"
         },
         {
            "code": "600109",
            "name": "国金证券"
         },
         {
            "code": "600105",
            "name": "永鼎股份"
         },
         {
            "code": "600104",
            "name": "上汽集团"
         }
      ],
      "p51": [
         {
            "code": "000426",
            "name": "兴业银锡"
         },
         {
            "code": "000425",
            "name": "徐工机械"
         },
         {
            "code": "000423",
            "name": "东阿阿胶"
         },
         {
            "code": "000415",
            "name": "渤海租赁"
         },
         {
            "code": "000402",
            "name": "金 融 街"
         },
         {
            "code": "000401",
            "name": "金隅冀东"
         },
         {
            "code": "000400",
            "name": "许继电气"
         },
         {
            "code": "000338",
            "name": "潍柴动力"
         },
         {
            "code": "000333",
            "name": "美的集团"
         },
         {
            "code": "000301",
            "name": "东方盛虹"
         },
         {
            "code": "000166",
            "name": "申万宏源"
         },
         {
            "code": "000158",
            "name": "常山北明"
         },
         {
            "code": "000157",
            "name": "中联重科"
         },
         {
            "code": "000156",
            "name": "华数传媒"
         },
         {
            "code": "000100",
            "name": "TCL科技"
         },
         {
            "code": "000090",
            "name": "天健集团"
         },
         {
            "code": "000089",
            "name": "深圳机场"
         },
         {
            "code": "000088",
            "name": "盐 田 港"
         },
         {
            "code": "000078",
            "name": "海王生物"
         },
         {
            "code": "000070",
            "name": "特发信息"
         }
      ],
      "p12": [
         {
            "code": "601166",
            "name": "兴业银行"
         },
         {
            "code": "601162",
            "name": "天风证券"
         },
         {
            "code": "601158",
            "name": "重庆水务"
         },
         {
            "code": "601155",
            "name": "新城控股"
         },
         {
            "code": "601139",
            "name": "深圳燃气"
         },
         {
            "code": "601138",
            "name": "工业富联"
         },
         {
            "code": "601128",
            "name": "常熟银行"
         },
         {
            "code": "601127",
            "name": "赛力斯"
         },
         {
            "code": "601117",
            "name": "中国化学"
         },
         {
            "code": "601111",
            "name": "中国国航"
         },
         {
            "code": "601108",
            "name": "财通证券"
         },
         {
            "code": "601107",
            "name": "四川成渝"
         },
         {
            "code": "601100",
            "name": "恒立液压"
         },
         {
            "code": "601099",
            "name": "太平洋"
         },
         {
            "code": "601098",
            "name": "中南传媒"
         },
         {
            "code": "601088",
            "name": "中国神华"
         },
         {
            "code": "601069",
            "name": "西部黄金"
         },
         {
            "code": "601068",
            "name": "中铝国际"
         },
         {
            "code": "601066",
            "name": "中信建投"
         },
         {
            "code": "601058",
            "name": "赛轮轮胎"
         }
      ],
      "p36": [
         {
            "code": "002408",
            "name": "齐翔腾达"
         },
         {
            "code": "002407",
            "name": "多氟多"
         },
         {
            "code": "002405",
            "name": "四维图新"
         },
         {
            "code": "002402",
            "name": "和而泰"
         },
         {
            "code": "002399",
            "name": "海普瑞"
         },
         {
            "code": "002396",
            "name": "星网锐捷"
         },
         {
            "code": "002390",
            "name": "信邦制药"
         },
         {
            "code": "002389",
            "name": "航天彩虹"
         },
         {
            "code": "002387",
            "name": "维信诺"
         },
         {
            "code": "002385",
            "name": "大北农"
         },
         {
            "code": "002384",
            "name": "东山精密"
         },
         {
            "code": "002383",
            "name": "合众思壮"
         },
         {
            "code": "002382",
            "name": "蓝帆医疗"
         },
         {
            "code": "002376",
            "name": "新北洋"
         },
         {
            "code": "002375",
            "name": "亚厦股份"
         },
         {
            "code": "002373",
            "name": "千方科技"
         },
         {
            "code": "002372",
            "name": "伟星新材"
         },
         {
            "code": "002371",
            "name": "北方华创"
         },
         {
            "code": "002370",
            "name": "亚太药业"
         },
         {
            "code": "002368",
            "name": "太极股份"
         }
      ],
      "p39": [
         {
            "code": "002244",
            "name": "滨江集团"
         },
         {
            "code": "002242",
            "name": "九阳股份"
         },
         {
            "code": "002241",
            "name": "歌尔股份"
         },
         {
            "code": "002237",
            "name": "恒邦股份"
         },
         {
            "code": "002236",
            "name": "大华股份"
         },
         {
            "code": "002233",
            "name": "塔牌集团"
         },
         {
            "code": "002230",
            "name": "科大讯飞"
         },
         {
            "code": "002226",
            "name": "江南化工"
         },
         {
            "code": "002223",
            "name": "鱼跃医疗"
         },
         {
            "code": "002217",
            "name": "合力泰"
         },
         {
            "code": "002215",
            "name": "诺 普 信"
         },
         {
            "code": "002212",
            "name": "天融信"
         },
         {
            "code": "002204",
            "name": "大连重工"
         },
         {
            "code": "002203",
            "name": "海亮股份"
         },
         {
            "code": "002202",
            "name": "金风科技"
         },
         {
            "code": "002195",
            "name": "岩山科技"
         },
         {
            "code": "002192",
            "name": "融捷股份"
         },
         {
            "code": "002191",
            "name": "劲嘉股份"
         },
         {
            "code": "002185",
            "name": "华天科技"
         },
         {
            "code": "002183",
            "name": "怡 亚 通"
         }
      ]
   }
}